dbox/__init__.py
dbox/addressinfo.py
dbox/bankinfo.py
dbox/cache.py
dbox/db_oper.py
dbox/encrypt.py
dbox/feishu.py
dbox/file.py
dbox/flow.py
dbox/git.py
dbox/gitea.py
dbox/github.py
dbox/message.py
dbox/my_http.py
dbox/net.py
dbox/samba.py
dbox/testdata.py
dbox/time.py
dbox/utils.py
dbox/windows.py
dbox-2025.10.23.1.dist-info/licenses/LICENSE
dbox-2025.10.23.1.dist-info/METADATA
dbox-2025.10.23.1.dist-info/WHEEL
dbox-2025.10.23.1.dist-info/top_level.txt
dbox-2025.10.23.1.dist-info/RECORD
