Metadata-Version: 2.4
Name: dbox
Version: 2025.10.23.1
Summary: Personal method encapsulation
Home-page: https://github.com/Deng2016/dbox
Author: dqy
Author-email: yu12377@163.com
Classifier: Programming Language :: Python
Classifier: Programming Language :: Python :: Implementation
Classifier: Programming Language :: Python :: 3.12
Classifier: Programming Language :: Python :: 3.13
Classifier: Topic :: Software Development :: Libraries
Requires-Python: >=3.12
License-File: LICENSE
Requires-Dist: requests~=2.32.4
Requires-Dist: redis~=6.2.0
Requires-Dist: pycryptodome~=3.23.0
Requires-Dist: xpinyin~=0.7.7
Requires-Dist: pysmb~=1.2.11
Requires-Dist: pyjwt~=2.10.1
Requires-Dist: pytz~=2025.2
Dynamic: author
Dynamic: author-email
Dynamic: classifier
Dynamic: description
Dynamic: description-content-type
Dynamic: home-page
Dynamic: license-file
Dynamic: requires-dist
Dynamic: requires-python
Dynamic: summary
